Metadata-Version: 1.2
Name: attention-sampling
Version: 0.2
Summary: Train networks on large data using attention sampling.
Home-page: http://www.idiap.ch/~katharas/
Maintainer: Angelos Katharopoulos
Maintainer-email: angelos.katharopoulos@idiap.ch
License: MIT
Platform: UNKNOWN
Classifier: Intended Audience :: Science/Research
Classifier: Intended Audience :: Developers
Classifier: License :: OSI Approved :: MIT License
Classifier: Topic :: Scientific/Engineering
Classifier: Programming Language :: Python
Classifier: Programming Language :: Python :: 3
Classifier: Programming Language :: Python :: 3.6
